README.txt
buildout.cfg
setup.py
wc/__init__.py
wc.worldcookeryskin.egg-info/PKG-INFO
wc.worldcookeryskin.egg-info/SOURCES.txt
wc.worldcookeryskin.egg-info/dependency_links.txt
wc.worldcookeryskin.egg-info/namespace_packages.txt
wc.worldcookeryskin.egg-info/not-zip-safe
wc.worldcookeryskin.egg-info/requires.txt
wc.worldcookeryskin.egg-info/top_level.txt
wc/worldcookeryskin/__init__.py
wc/worldcookeryskin/actions.pt
wc/worldcookeryskin/addmenu.pt
wc/worldcookeryskin/breadcrumbs.pt
wc/worldcookeryskin/configure.zcml
wc/worldcookeryskin/interfaces.py
wc/worldcookeryskin/login.pt
wc/worldcookeryskin/logo.pt
wc/worldcookeryskin/manager.py
wc/worldcookeryskin/standardmacros.py
wc/worldcookeryskin/tabs.pt
wc/worldcookeryskin/wc.worldcookeryskin-configure.zcml
wc/worldcookeryskin/worldcookery.pt
wc/worldcookeryskin/resources/background.png
wc/worldcookeryskin/resources/icon.png
wc/worldcookeryskin/resources/logobg.png
wc/worldcookeryskin/resources/worldcookery.css
wc/worldcookeryskin/resources/worldcookery.png
