Metadata-Version: 1.0
Name: wc.worldcookeryskin
Version: 3.9.1
Summary: Zope 3 skin for WorldCookery-like applications
Home-page: http://worldcookery.com/Downloads
Author: Philipp von Weitershausen
Author-email: philipp@weitershausen.de
License: UNKNOWN
Platform: UNKNOWN
Classifier: Development Status :: 5 - Production/Stable
Classifier: Environment :: Web Environment
Classifier: Framework :: Zope3
Classifier: Intended Audience :: Developers
